fbench/__init__.py
fbench/function.py
fbench/structure.py
fbench/validation.py
fbench/viz.py
fbench-1.0.1.dist-info/WHEEL
fbench-1.0.1.dist-info/LICENSE
fbench-1.0.1.dist-info/METADATA
fbench-1.0.1.dist-info/LICENSES/NUMPY_LICENSE
fbench-1.0.1.dist-info/RECORD
