Metadata-Version: 2.1
Name: fbench
Version: 1.0.1
Summary: A collection of benchmark functions.
Home-page: https://github.com/estripling/fbench
License: BSD 3-Clause
Keywords: fbench
Author: fBench Developers
Requires-Python: >=3.8,<4.0
Classifier: License :: Other/Proprietary License
Classifier: Programming Language :: Python :: 3
Classifier: Programming Language :: Python :: 3.8
Classifier: Programming Language :: Python :: 3.9
Classifier: Programming Language :: Python :: 3.10
Classifier: Programming Language :: Python :: 3.11
Classifier: Programming Language :: Python :: 3
Requires-Dist: bumbag (>=5.0.0,<6.0.0)
Requires-Dist: matplotlib (>=3.7.1,<4.0.0)
Requires-Dist: numpy (>=1.24.2,<2.0.0)
Project-URL: Documentation, https://fbench.readthedocs.io/en/stable/
Project-URL: Repository, https://github.com/estripling/fbench
